mcp_proxy_stateless-0.1.4.dist-info/licenses/LICENSE
post_class/mcp_proxy_stateless/__init__.py
post_class/mcp_proxy_stateless/main.py
mcp_proxy_stateless-0.1.4.dist-info/METADATA
mcp_proxy_stateless-0.1.4.dist-info/WHEEL
mcp_proxy_stateless-0.1.4.dist-info/entry_points.txt
mcp_proxy_stateless-0.1.4.dist-info/top_level.txt
mcp_proxy_stateless-0.1.4.dist-info/RECORD
