Metadata-Version: 2.4
Name: mcp-proxy-stateless
Version: 0.1.4
Summary: Stdio-to-StreamableHTTP MCP proxy that enforces stateless requests.
Project-URL: Homepage, https://github.com/post-class/mcp_proxy_stateless
Project-URL: Repository, https://github.com/post-class/mcp_proxy_stateless
Requires-Python: >=3.11
License-File: LICENSE
Requires-Dist: httpx>=0.28.1
Requires-Dist: mcp>=1.8.0
Dynamic: license-file
